{"returnsForSmallBusiness":{"isObligated":false,"isTrial":false,"isActive":false},"avalaraForSmallBusiness":{"isObligated":false,"isTrial":false,"isActive":false},"managedReturns":{"isObligated":true,"isTrial":false,"termStart":"2025-08-28T00:00:00Z","termEnd":"2026-08-27T00:00:00Z","isActive":true},"customerObligations":[{"obligationSource":"Salesforce","Id":"aLZUz000002R2W2OAK","productCatalogId":"LR_ST_REG_DOM","itemName":"Domestic","isAccessPermitted":true,"accessStart":"2025-04-10","termStart":"2025-04-10","termEnd":"2026-04-09","initialTerm":null,"renewalTerm":null,"connectorId":null,"connectorName":null,"connectorMarketplaceName":null,"connectorLevel":null,"connectorPOS":null,"connectorIsExtractor":null,"billingFrequency":null,"quantity":null,"price":1612.38,"OveragePrice":null,"OrgId":"66d0622c764c481bf7a86845","TenantId":"66d0622c764c481bf7a86846"},{"obligationSource":"Salesforce","Id":"aLZUz000002q35VOAQ","productCatalogId":"CDM_ECM_PRM_CEM_OVG","itemName":"Overage","isAccessPermitted":true,"accessStart":"2025-08-28","termStart":"2025-08-28","termEnd":"2026-08-27","initialTerm":12,"renewalTerm":12,"connectorId":null,"connectorName":null,"connectorMarketplaceName":null,"connectorLevel":null,"connectorPOS":null,"connectorIsExtractor":null,"billingFrequency":"Annual","quantity":1,"price":0,"OveragePrice":null,"OrgId":"66d0622c764c481bf7a86845","TenantId":"66d0622c764c481bf7a86846"},{"obligationSource":"Salesforce","Id":"aLZUz000002q35WOAQ","productCatalogId":"CDM_ECM_PRM_CEM_SVC","itemName":"Service Fee","isAccessPermitted":true,"accessStart":"2025-08-28","termStart":"2025-08-28","termEnd":"2026-08-27","initialTerm":12,"renewalTerm":12,"connectorId":null,"connectorName":null,"connectorMarketplaceName":null,"connectorLevel":null,"connectorPOS":null,"connectorIsExtractor":null,"billingFrequency":"Annual","quantity":1,"price":4334.1,"OveragePrice":null,"OrgId":"66d0622c764c481bf7a86845","TenantId":"66d0622c764c481bf7a86846"},{"obligationSource":"Salesforce","Id":"aLZUz000002q35XOAQ","productCatalogId":"RR_SST_VOL","itemName":"Volunteer Returns","isAccessPermitted":true,"accessStart":"2025-08-28","termStart":"2025-08-28","termEnd":"2026-08-27","initialTerm":12,"renewalTerm":12,"connectorId":null,"connectorName":null,"connectorMarketplaceName":null,"connectorLevel":null,"connectorPOS":null,"connectorIsExtractor":null,"billingFrequency":"Annual","quantity":1,"price":0,"OveragePrice":null,"OrgId":"66d0622c764c481bf7a86845","TenantId":"66d0622c764c481bf7a86846"},{"obligationSource":"Salesforce","Id":"aLZUz000002q35YOAQ","productCatalogId":"RR_SST_NONVOL","itemName":"Non-Volunteer Returns","isAccessPermitted":true,"accessStart":"2025-08-28","termStart":"2025-08-28","termEnd":"2026-08-27","initialTerm":12,"renewalTerm":12,"connectorId":null,"connectorName":null,"connectorMarketplaceName":null,"connectorLevel":null,"connectorPOS":null,"connectorIsExtractor":null,"billingFrequency":"Annual","quantity":1,"price":0,"OveragePrice":null,"OrgId":"66d0622c764c481bf7a86845","TenantId":"66d0622c764c481bf7a86846"},{"obligationSource":"Salesforce","Id":"aLZUz000002q35ZOAQ","productCatalogId":"RR_MRS_PRM_PPD_PLN_LL","itemName":"Prepaid Planned Late-Locking Fee","isAccessPermitted":true,"accessStart":"2025-08-28","termStart":"2025-08-28","termEnd":"2026-08-27","initialTerm":12,"renewalTerm":12,"connectorId":null,"connectorName":null,"connectorMarketplaceName":null,"connectorLevel":null,"connectorPOS":null,"connectorIsExtractor":null,"billingFrequency":"Annual","quantity":1,"price":0,"OveragePrice":null,"OrgId":"66d0622c764c481bf7a86845","TenantId":"66d0622c764c481bf7a86846"},{"obligationSource":"Salesforce","Id":"aLZUz000002q35aOAA","productCatalogId":"RR_MRS_PRM_PPD_UNPLN_LL","itemName":"Prepaid Unplanned Late Locking Fee","isAccessPermitted":true,"accessStart":"2025-08-28","termStart":"2025-08-28","termEnd":"2026-08-27","initialTerm":12,"renewalTerm":12,"connectorId":null,"connectorName":null,"connectorMarketplaceName":null,"connectorLevel":null,"connectorPOS":null,"connectorIsExtractor":null,"billingFrequency":"Annual","quantity":1,"price":0,"OveragePrice":null,"OrgId":"66d0622c764c481bf7a86845","TenantId":"66d0622c764c481bf7a86846"},{"obligationSource":"Salesforce","Id":"aLZUz000002q35bOAA","productCatalogId":"RR_MRS_PRM_PPD_OVG","itemName":"Prepaid Premium-Overage","isAccessPermitted":true,"accessStart":"2025-08-28","termStart":"2025-08-28","termEnd":"2026-08-27","initialTerm":12,"renewalTerm":12,"connectorId":null,"connectorName":null,"connectorMarketplaceName":null,"connectorLevel":null,"connectorPOS":null,"connectorIsExtractor":null,"billingFrequency":"Annual","quantity":1,"price":0,"OveragePrice":null,"OrgId":"66d0622c764c481bf7a86845","TenantId":"66d0622c764c481bf7a86846"},{"obligationSource":"Salesforce","Id":"aLZUz000002q35cOAA","productCatalogId":"RR_LFF_USG","itemName":"Late Funder Fee","isAccessPermitted":true,"accessStart":"2025-08-28","termStart":"2025-08-28","termEnd":"2026-08-27","initialTerm":12,"renewalTerm":12,"connectorId":null,"connectorName":null,"connectorMarketplaceName":null,"connectorLevel":null,"connectorPOS":null,"connectorIsExtractor":null,"billingFrequency":"Annual","quantity":1,"price":0,"OveragePrice":null,"OrgId":"66d0622c764c481bf7a86845","TenantId":"66d0622c764c481bf7a86846"},{"obligationSource":"Salesforce","Id":"aLZUz000002q35dOAA","productCatalogId":"RR_MRS_PRM_PPD_SVC","itemName":"Prepaid Service","isAccessPermitted":true,"accessStart":"2025-08-28","termStart":"2025-08-28","termEnd":"2026-08-27","initialTerm":12,"renewalTerm":12,"connectorId":null,"connectorName":null,"connectorMarketplaceName":null,"connectorLevel":null,"connectorPOS":null,"connectorIsExtractor":null,"billingFrequency":"Annual","quantity":458,"price":25394.69,"OveragePrice":null,"OrgId":"66d0622c764c481bf7a86845","TenantId":"66d0622c764c481bf7a86846"},{"obligationSource":"Salesforce","Id":"aLZUz000002q35eOAA","productCatalogId":"RR_MRS_PRM_PPD_UPG","itemName":"Upgrade Fee","isAccessPermitted":true,"accessStart":"2025-08-28","termStart":"2025-08-28","termEnd":"2026-08-27","initialTerm":null,"renewalTerm":null,"connectorId":null,"connectorName":null,"connectorMarketplaceName":null,"connectorLevel":null,"connectorPOS":null,"connectorIsExtractor":null,"billingFrequency":null,"quantity":null,"price":231,"OveragePrice":null,"OrgId":"66d0622c764c481bf7a86845","TenantId":"66d0622c764c481bf7a86846"},{"obligationSource":"Salesforce","Id":"aLZUz000002q35fOAA","productCatalogId":"CALC_AVTX_OVG","itemName":"Overage","isAccessPermitted":true,"accessStart":"2025-08-28","termStart":"2025-08-28","termEnd":"2026-08-27","initialTerm":12,"renewalTerm":12,"connectorId":null,"connectorName":null,"connectorMarketplaceName":null,"connectorLevel":null,"connectorPOS":null,"connectorIsExtractor":null,"billingFrequency":"Annual","quantity":1,"price":0,"OveragePrice":null,"OrgId":"66d0622c764c481bf7a86845","TenantId":"66d0622c764c481bf7a86846"},{"obligationSource":"Salesforce","Id":"aLZUz000002q35gOAA","productCatalogId":"CALC_AVTX_CONN","itemName":"Connector for Avatax","isAccessPermitted":true,"accessStart":"2025-08-28","termStart":"2025-08-28","termEnd":"2026-08-27","initialTerm":12,"renewalTerm":12,"connectorId":"a0nUz000003MOA1IAO","connectorName":"Avalara for Shopify","connectorMarketplaceName":"Avalara for Shopify","connectorLevel":"Level 2","connectorPOS":false,"connectorIsExtractor":"No","billingFrequency":"Annual","quantity":1,"price":678.96,"OveragePrice":null,"OrgId":"66d0622c764c481bf7a86845","TenantId":"66d0622c764c481bf7a86846"},{"obligationSource":"Salesforce","Id":"aLZUz000002q35hOAA","productCatalogId":"CALC_AVTX_SBX_SVC","itemName":"Recurring Sandbox","isAccessPermitted":true,"accessStart":"2025-08-28","termStart":"2025-08-28","termEnd":"2026-08-27","initialTerm":12,"renewalTerm":12,"connectorId":null,"connectorName":null,"connectorMarketplaceName":null,"connectorLevel":null,"connectorPOS":null,"connectorIsExtractor":null,"billingFrequency":"Annual","quantity":1,"price":2106.98,"OveragePrice":null,"OrgId":"66d0622c764c481bf7a86845","TenantId":"66d0622c764c481bf7a86846"},{"obligationSource":"Salesforce","Id":"aLZUz000002q35iOAA","productCatalogId":"CALC_AVTX_CONN","itemName":"Connector for Avatax","isAccessPermitted":true,"accessStart":"2025-08-28","termStart":"2025-08-28","termEnd":"2026-08-27","initialTerm":12,"renewalTerm":12,"connectorId":"a0n4000000ChMwnAAF","connectorName":"NetSuite OneWorld","connectorMarketplaceName":"NetSuite OneWorld","connectorLevel":"Level 3","connectorPOS":true,"connectorIsExtractor":"No","billingFrequency":"Annual","quantity":1,"price":4390.51,"OveragePrice":null,"OrgId":"66d0622c764c481bf7a86845","TenantId":"66d0622c764c481bf7a86846"},{"obligationSource":"Salesforce","Id":"aLZUz000002q35jOAA","productCatalogId":"CALC_AVTX_SVC","itemName":"Service","isAccessPermitted":true,"accessStart":"2025-08-28","termStart":"2025-08-28","termEnd":"2026-08-27","initialTerm":12,"renewalTerm":12,"connectorId":null,"connectorName":null,"connectorMarketplaceName":null,"connectorLevel":null,"connectorPOS":null,"connectorIsExtractor":null,"billingFrequency":"Annual","quantity":1,"price":7091.88,"OveragePrice":null,"OrgId":"66d0622c764c481bf7a86845","TenantId":"66d0622c764c481bf7a86846"},{"obligationSource":"Salesforce","Id":"aLZUz00000309T1OAI","productCatalogId":"LR_ST_REG_DOM","itemName":"Domestic","isAccessPermitted":true,"accessStart":"2025-10-22","termStart":"2025-10-22","termEnd":"2026-10-21","initialTerm":null,"renewalTerm":null,"connectorId":null,"connectorName":null,"connectorMarketplaceName":null,"connectorLevel":null,"connectorPOS":null,"connectorIsExtractor":null,"billingFrequency":null,"quantity":null,"price":403.1,"OveragePrice":null,"OrgId":"66d0622c764c481bf7a86845","TenantId":"66d0622c764c481bf7a86846"},{"obligationSource":"Salesforce","Id":"aLZUz0000036SHdOAM","productCatalogId":"LR_ST_DREG","itemName":"De-Registration","isAccessPermitted":true,"accessStart":"2025-11-21","termStart":"2025-11-21","termEnd":"2026-08-27","initialTerm":null,"renewalTerm":null,"connectorId":null,"connectorName":null,"connectorMarketplaceName":null,"connectorLevel":null,"connectorPOS":null,"connectorIsExtractor":null,"billingFrequency":null,"quantity":null,"price":16526.9,"OveragePrice":null,"OrgId":"66d0622c764c481bf7a86845","TenantId":"66d0622c764c481bf7a86846"},{"obligationSource":"Salesforce","Id":"aLZUz0000036SHeOAM","productCatalogId":"LR_ST_REG_DOM","itemName":"Domestic","isAccessPermitted":true,"accessStart":"2025-11-21","termStart":"2025-11-21","termEnd":"2026-08-27","initialTerm":null,"renewalTerm":null,"connectorId":null,"connectorName":null,"connectorMarketplaceName":null,"connectorLevel":null,"connectorPOS":null,"connectorIsExtractor":null,"billingFrequency":null,"quantity":null,"price":8868.09,"OveragePrice":null,"OrgId":"66d0622c764c481bf7a86845","TenantId":"66d0622c764c481bf7a86846"},{"obligationSource":"Salesforce","Id":"aLZUz000003Gf2HOAS","productCatalogId":"LR_ST_DREG","itemName":"De-Registration","isAccessPermitted":true,"accessStart":"2026-01-13","termStart":"2026-01-13","termEnd":"2027-01-12","initialTerm":null,"renewalTerm":null,"connectorId":null,"connectorName":null,"connectorMarketplaceName":null,"connectorLevel":null,"connectorPOS":null,"connectorIsExtractor":null,"billingFrequency":null,"quantity":null,"price":9271.19,"OveragePrice":null,"OrgId":"66d0622c764c481bf7a86845","TenantId":"66d0622c764c481bf7a86846"},{"obligationSource":"Salesforce","Id":"aLZUz000003Gf2IOAS","productCatalogId":"LR_ST_REG_DOM","itemName":"Domestic","isAccessPermitted":true,"accessStart":"2026-01-13","termStart":"2026-01-13","termEnd":"2027-01-12","initialTerm":null,"renewalTerm":null,"connectorId":null,"connectorName":null,"connectorMarketplaceName":null,"connectorLevel":null,"connectorPOS":null,"connectorIsExtractor":null,"billingFrequency":null,"quantity":null,"price":9287.31,"OveragePrice":null,"OrgId":"66d0622c764c481bf7a86845","TenantId":"66d0622c764c481bf7a86846"}]}