{
  "companies": {
    "active_company_codes": [
      "MUDMIXERLLCNEW",
      "DEFAULT"
    ],
    "company_count": 3,
    "default_company_code": "DEFAULT"
  },
  "dump_dir": "/Users/wesmelton/Documents/Dev/MudMixer/avalara/exports/data-dumps/2026-03-13",
  "filing_calendars": {
    "answer_row_count": 962,
    "filing_calendar_row_count": 80,
    "frequency_counts": {
      "Annually": 7,
      "InverseQuarterly": 1,
      "Monthly": 60,
      "Quarterly": 12
    },
    "status_counts": {
      "Active": 18,
      "Expired": 62
    },
    "top_tax_forms": [
      [
        "USNMTRD41413",
        3
      ],
      [
        "USNVTXR01",
        3
      ],
      [
        "USMAST9",
        2
      ],
      [
        "USNCE500E536",
        2
      ],
      [
        "USOHUST1",
        2
      ],
      [
        "USTX0111401116",
        2
      ],
      [
        "USTNSLS450",
        2
      ],
      [
        "USINST103",
        2
      ],
      [
        "USAL2620",
        2
      ],
      [
        "USKY51A102",
        2
      ],
      [
        "USWAMULTIPURPOSEST",
        2
      ],
      [
        "USALMADISONCOUNTY",
        2
      ],
      [
        "USMS72110015",
        2
      ],
      [
        "USARET1",
        1
      ],
      [
        "USHIG45",
        1
      ],
      [
        "USWYF41",
        1
      ],
      [
        "USCACDTFA401A2",
        1
      ],
      [
        "USCODR0100",
        1
      ],
      [
        "USGAST3SALES",
        1
      ],
      [
        "USKSCT9U",
        1
      ],
      [
        "USFLDR15",
        1
      ],
      [
        "USILST1",
        1
      ],
      [
        "USID850",
        1
      ],
      [
        "USMEST7",
        1
      ],
      [
        "USMI5080SU",
        1
      ]
    ]
  },
  "new_company_settings": {
    "company_id": 6550943,
    "is_ssgl_company": true,
    "ssgl_countries": [
      "CA"
    ],
    "ssgl_id": 8710115,
    "ssgl_modified_date": "2026-02-19T02:30:14.39",
    "ssgl_name": "ssgl",
    "ssgl_set": "avalara:returns",
    "two_factor_alias_configured": false
  },
  "obligations": {
    "connectors": {
      "Avalara for Shopify": 1,
      "NONE": 19,
      "NetSuite OneWorld": 1
    },
    "customer_obligation_count": 21,
    "managed_returns": {
      "isActive": true,
      "isObligated": true,
      "isTrial": false,
      "termEnd": "2026-08-27T00:00:00Z",
      "termStart": "2025-08-28T00:00:00Z"
    },
    "obligation_sources": {
      "Salesforce": 21
    },
    "products": {
      "CALC_AVTX_CONN": 2,
      "CALC_AVTX_OVG": 1,
      "CALC_AVTX_SBX_SVC": 1,
      "CALC_AVTX_SVC": 1,
      "CDM_ECM_PRM_CEM_OVG": 1,
      "CDM_ECM_PRM_CEM_SVC": 1,
      "LR_ST_DREG": 2,
      "LR_ST_REG_DOM": 4,
      "RR_LFF_USG": 1,
      "RR_MRS_PRM_PPD_OVG": 1,
      "RR_MRS_PRM_PPD_PLN_LL": 1,
      "RR_MRS_PRM_PPD_SVC": 1,
      "RR_MRS_PRM_PPD_UNPLN_LL": 1,
      "RR_MRS_PRM_PPD_UPG": 1,
      "RR_SST_NONVOL": 1,
      "RR_SST_VOL": 1
    }
  }
}